aws_lib/__init__.py
aws_lib/sh_bh.py
sh_bh-0.0.1.dist-info/METADATA
sh_bh-0.0.1.dist-info/WHEEL
sh_bh-0.0.1.dist-info/licence.txt
sh_bh-0.0.1.dist-info/top_level.txt
sh_bh-0.0.1.dist-info/RECORD
