Metadata-Version: 2.1
Name: sh-bh
Version: 0.0.1
Summary: sh_bh
Author: Shubham
Author-email: shubhambhosale1920@gmail.com
Keywords: AWS,S3,EC2,IAMuser,Shubham-bh
Classifier: Development Status :: 1 - Planning
Classifier: Intended Audience :: Developers
Classifier: Programming Language :: Python :: 3
Classifier: Operating System :: Unix
Classifier: Operating System :: MacOS :: MacOS X
Classifier: Operating System :: Microsoft :: Windows
License-File: licence.txt
